polar_python/__init__.py
polar_python/constants.py
polar_python/device.py
polar_python/exceptions.py
polar_python/utils.py
polar_python/parsers/__init__.py
polar_python/parsers/accelerometer.py
polar_python/parsers/bluetooth.py
polar_python/parsers/common.py
polar_python/parsers/compression.py
polar_python/parsers/ecg.py
polar_python/parsers/heartrate.py
polar_python/parsers/pmd.py
polar_python/parsers/ppi.py
polar_python-0.0.5.dist-info/licenses/LICENSE
polar_python-0.0.5.dist-info/METADATA
polar_python-0.0.5.dist-info/WHEEL
polar_python-0.0.5.dist-info/top_level.txt
polar_python-0.0.5.dist-info/RECORD
