Metadata-Version: 2.4
Name: polar-python
Version: 0.0.5
Summary: polar-python is a Python library for connecting to Polar devices via Bluetooth Low Energy (BLE) using Bleak. It allows querying device capabilities (e.g., ECG, ACC, PPG), exploring configurable options, and streaming parsed data through callback functions.
Home-page: https://github.com/zHElEARN/polar-python
Author: Zhe_Learn
Author-email: personal@zhelearn.com
License: MIT
Classifier: Programming Language :: Python :: 3
Classifier: License :: OSI Approved :: MIT License
Classifier: Operating System :: OS Independent
Classifier: Development Status :: 3 - Alpha
Classifier: Intended Audience :: Developers
Classifier: Topic :: Software Development :: Libraries :: Python Modules
Requires-Python: >=3.6
License-File: LICENSE
Requires-Dist: bleak
Dynamic: author
Dynamic: author-email
Dynamic: classifier
Dynamic: description
Dynamic: description-content-type
Dynamic: home-page
Dynamic: license
Dynamic: license-file
Dynamic: requires-dist
Dynamic: requires-python
Dynamic: summary
